MANIFEST.in
README.txt
setup.py
docs/HISTORY.txt
src/silva/__init__.py
src/silva.batch.egg-info/PKG-INFO
src/silva.batch.egg-info/SOURCES.txt
src/silva.batch.egg-info/dependency_links.txt
src/silva.batch.egg-info/namespace_packages.txt
src/silva.batch.egg-info/not-zip-safe
src/silva.batch.egg-info/requires.txt
src/silva.batch.egg-info/top_level.txt
src/silva/batch/__init__.py
src/silva/batch/configure.zcml
src/silva/batch/overrides.zcml
src/silva/batch/views.py