Metadata-Version: 1.1
Name: silva.batch
Version: 1.1
Summary: Batch integration for Silva CMS
Home-page: https://github.com/silvacms/silva.batch
Author: Antonin Amand
Author-email: info@infrae.com
License: BSD
Keywords: batch silva pagination
Platform: UNKNOWN
Classifier: Framework :: Zope2
Classifier: Programming Language :: Python
Classifier: Topic :: Software Development :: Libraries :: Python Modules
Classifier: License :: OSI Approved :: BSD License
